hanoitoys/Hanoi.py
hanoitoys/HanoiClassical.py
hanoitoys/HanoiIdlePeg.py
hanoitoys/HanoiNR.py
hanoitoys/HanoiOlive.py
hanoitoys/__init__.py
hanoitoys-0.1.3.dist-info/LICENSE.txt
hanoitoys-0.1.3.dist-info/METADATA
hanoitoys-0.1.3.dist-info/WHEEL
hanoitoys-0.1.3.dist-info/top_level.txt
hanoitoys-0.1.3.dist-info/RECORD
