Metadata-Version: 2.1
Name: hanoitoys
Version: 0.1.3
Summary: A collection of Tower of Hanoi solutions including the Steward Frame algorithm.
Home-page: https://github.com/DanLBates/hanoitoys
Author: Daniel L. Bates
Author-email: danbates@verizon.net
License: UNKNOWN
Keywords: 'Tower','of','Hanoi','Lucas','Brahma','Brahman','Steward','Frame','dan.bates'
Platform: UNKNOWN
Classifier: Programming Language :: Python :: 3
Classifier: License :: OSI Approved :: MIT License
Classifier: Operating System :: OS Independent
Classifier: Intended Audience :: End Users/Desktop
Requires-Python: >=3.8
License-File: LICENSE.txt
